artefacts_toolkit_utilities/__init__.py
artefacts_toolkit_utilities/exceptions.py
artefacts_toolkit_utilities/utils.py
artefacts_toolkit_utilities/version.py
artefacts_toolkit_utilities-0.3.0.dist-info/METADATA
artefacts_toolkit_utilities-0.3.0.dist-info/WHEEL
artefacts_toolkit_utilities-0.3.0.dist-info/top_level.txt
artefacts_toolkit_utilities-0.3.0.dist-info/RECORD
