Metadata-Version: 2.4
Name: artefacts_toolkit_utilities
Version: 0.3.0
Author-email: FD <fabian@artefacts.com>, AGC <alejandro@artefacts.com>, TN <tomo@artefacts.com>, EP <eric@artefacts.com>
Project-URL: Homepage, https://github.com/art-e-fact/artefacts-toolkit-utilities
Project-URL: Bug Tracker, https://github.com/art-e-fact/artefacts-toolkit-utilities
Classifier: Programming Language :: Python :: 3
Classifier: License :: OSI Approved :: Apache Software License
Classifier: Operating System :: OS Independent
Requires-Python: >=3.10
Provides-Extra: dev
Requires-Dist: build; extra == "dev"
Requires-Dist: pyre-check; extra == "dev"
Requires-Dist: pytest; extra == "dev"
Requires-Dist: pytest-cov; extra == "dev"
Requires-Dist: pytest-env; extra == "dev"
Requires-Dist: pytest-mock; extra == "dev"
Requires-Dist: ruff; extra == "dev"
Requires-Dist: setuptools-scm; extra == "dev"
Requires-Dist: twine; extra == "dev"
Requires-Dist: rosbags; extra == "dev"
